{
  "gitSyncId": "66b91aa416e9244321599197_53218286-1053-47cd-9322-981873b4c347",
  "id": "Returns Copy_utils.statusColor",
  "pluginId": "js-plugin",
  "pluginType": "JS",
  "unpublishedAction": {
    "actionConfiguration": {
      "encodeParamsToggle": true,
      "jsArguments": [
        {
          "name": "status"
        }
      ],
      "paginationType": "NONE",
      "timeoutInMillisecond": 10000
    },
    "collectionId": "Returns Copy_utils",
    "confirmBeforeExecute": false,
    "datasource": {
      "isAutoGenerated": false,
      "name": "UNUSED_DATASOURCE",
      "pluginId": "js-plugin"
    },
    "dynamicBindingPathList": [
      {
        "key": "body"
      }
    ],
    "executeOnLoad": false,
    "fullyQualifiedName": "utils.statusColor",
    "name": "statusColor",
    "pageId": "Returns Copy",
    "userSetOnLoad": false
  }
}